{"cameraMode":{"drawMode":0,"name":"Shaded","section":"Shading Mode"},"sceneLighting":false,"audioPlay":false,"sceneViewState":{"m_AlwaysRefresh":false,"showFog":false,"showSkybox":false,"showFlares":true,"showImageEffects":true,"showParticleSystems":true,"showVisualEffectGraphs":true,"m_FxEnabled":true},"in2DMode":false,"pivot":{"x":0.0,"y":0.24780325591564179,"z":4.470348358154297e-8},"rotation":{"x":-0.10012366622686386,"y":0.19626273214817048,"z":-0.02014990895986557,"w":-0.9752179384231567},"size":0.5203896164894104,"orthographic":false}